{
  "packets":{
    "actorList":["11534-0","11535-0","11536-0","14628-0","26424-0","26425-0","26426-0","29534-0","29535-0","29536-0","29537-0","29538-0","30742-0","30743-0","11537-0","11538-0","32996-0"],
    "ai":[],
    "cellChangeFrom":[],
    "cellChangeTo":["10153-0"],
    "container":["11534-0","11535-0","11536-0","14628-0","26424-0","26425-0","26426-0","29534-0","29535-0","29536-0","29537-0","29538-0","30742-0","30743-0","11537-0","11538-0","32996-0"],
    "death":[],
    "delete":[],
    "doorState":[],
    "equipment":["11534-0","11535-0","11536-0","14628-0","26424-0","26425-0","26426-0","29534-0","29535-0","29536-0","29537-0","29538-0","30742-0","30743-0"],
    "lock":[],
    "place":[],
    "position":["11534-0","11535-0","11536-0","11537-0","11538-0","14628-0","26424-0","26425-0","26426-0","29534-0","29535-0","29536-0","29537-0","29538-0","30742-0","30743-0","32996-0"],
    "scale":[],
    "spawn":[],
    "state":["29441-0","14628-0","26424-0","26425-0","26426-0","29538-0","30742-0","30743-0"],
    "statsDynamic":["11534-0","11535-0","11536-0","11537-0","11538-0","14628-0","26424-0","26425-0","26426-0","29534-0","29535-0","29536-0","29537-0","29538-0","30742-0","30743-0","32996-0"],
    "trap":[]
  },
  "entry":{
    "creationTime":1568869959,
    "description":"-20, 25"
  },
  "lastVisit":{
    "Dizzy":1568923496,
    "Tanis":1568940544,
    "Dr,Kups":1568923677
  },
  "recordLinks":[],
  "objectData":{
    "29441-0":{
      "refId":"ex_s_door_rigmor2",
      "state":false
    },
    "10153-0":{
      "cellChangeTo":"-20, 26"
    },
    "30742-0":{
      "refId":"bm_werewolf_skaal1f3",
      "location":{
        "posX":-158567.921875,
        "posZ":3013.1301269531,
        "posY":211031.84375,
        "rotX":0,
        "rotY":0,
        "rotZ":0
      },
      "stats":{
        "healthCurrent":337,
        "magickaCurrent":158,
        "healthModified":337,
        "fatigueBase":368,
        "magickaModified":158,
        "fatigueModified":368,
        "healthBase":337,
        "magickaBase":158,
        "fatigueCurrent":368
      },
      "equipment":[],
      "inventory":[],
      "state":false
    },
    "26425-0":{
      "refId":"bm_werewolf_skaal1d3",
      "location":{
        "posX":-159959.234375,
        "posZ":3008.6120605469,
        "posY":211847.125,
        "rotX":0,
        "rotY":0,
        "rotZ":0
      },
      "stats":{
        "healthCurrent":337,
        "magickaCurrent":158,
        "healthModified":337,
        "fatigueBase":368,
        "magickaModified":158,
        "fatigueModified":368,
        "healthBase":337,
        "magickaBase":158,
        "fatigueCurrent":368
      },
      "equipment":[],
      "inventory":[],
      "state":false
    },
    "11534-0":{
      "refId":"engar ice-mane",
      "location":{
        "posX":-159020.828125,
        "posZ":2988.5717773438,
        "posY":211000.234375,
        "rotX":-0.031647335737944,
        "rotY":0,
        "rotZ":-0.91409468650818
      },
      "stats":{
        "healthCurrent":394,
        "magickaCurrent":138,
        "healthModified":394,
        "fatigueBase":379,
        "fatigueModified":379,
        "healthBase":394,
        "magickaModified":138,
        "magickaBase":138,
        "fatigueCurrent":379
      },
      "equipment":[{
          "refId":"bm wolf cuirass",
          "count":1,
          "charge":-1,
          "enchantmentCharge":-1
        },{
          "refId":"bm wolf greaves",
          "count":1,
          "charge":-1,
          "enchantmentCharge":-1
        },{
          "refId":"bm wolf left pauldron",
          "count":1,
          "charge":-1,
          "enchantmentCharge":-1
        },{
          "refId":"bm wolf right pauldron",
          "count":1,
          "charge":-1,
          "enchantmentCharge":-1
        },{
          "refId":"bm wolf left gauntlet",
          "count":1,
          "charge":-1,
          "enchantmentCharge":-1
        },{
          "refId":"bm wolf right gauntlet",
          "count":1,
          "charge":-1,
          "enchantmentCharge":-1
        },{
          "refId":"bm wolf boots",
          "count":1,
          "charge":-1,
          "enchantmentCharge":-1
        },null,null,null,null,null,null,null,null,{
          "refId":"bm nordic silver claymore",
          "count":1,
          "charge":-1,
          "enchantmentCharge":-1
        }],
      "inventory":[{
          "refId":"bm wolf right gauntlet",
          "count":1,
          "charge":-1,
          "enchantmentCharge":-1,
          "soul":""
        },{
          "refId":"bm wolf left gauntlet",
          "count":1,
          "charge":-1,
          "enchantmentCharge":-1,
          "soul":""
        },{
          "refId":"bm wolf boots",
          "count":1,
          "charge":-1,
          "enchantmentCharge":-1,
          "soul":""
        },{
          "refId":"bm wolf greaves",
          "count":1,
          "charge":-1,
          "enchantmentCharge":-1,
          "soul":""
        },{
          "refId":"bm wolf right pauldron",
          "count":1,
          "charge":-1,
          "enchantmentCharge":-1,
          "soul":""
        },{
          "refId":"bm wolf left pauldron",
          "count":1,
          "charge":-1,
          "enchantmentCharge":-1,
          "soul":""
        },{
          "refId":"bm wolf cuirass",
          "count":1,
          "charge":-1,
          "enchantmentCharge":-1,
          "soul":""
        },{
          "refId":"gold_001",
          "count":105,
          "charge":-1,
          "enchantmentCharge":-1,
          "soul":""
        },{
          "refId":"bm nordic silver claymore",
          "count":1,
          "charge":-1,
          "enchantmentCharge":-1,
          "soul":""
        }]
    },
    "26424-0":{
      "refId":"bm_werewolf_skaal1c3",
      "location":{
        "posX":-159203.953125,
        "posZ":2985.0002441406,
        "posY":211577.984375,
        "rotX":0,
        "rotY":0,
        "rotZ":0
      },
      "stats":{
        "healthCurrent":337,
        "magickaCurrent":158,
        "healthModified":337,
        "fatigueBase":368,
        "magickaModified":158,
        "fatigueModified":368,
        "healthBase":337,
        "magickaBase":158,
        "fatigueCurrent":368
      },
      "equipment":[],
      "inventory":[],
      "state":false
    },
    "29538-0":{
      "refId":"bm_werewolf_skaal1b3",
      "location":{
        "posX":-158552.078125,
        "posZ":2929,
        "posY":212698.296875,
        "rotX":0,
        "rotY":0,
        "rotZ":0
      },
      "stats":{
        "healthCurrent":337,
        "magickaCurrent":158,
        "healthModified":337,
        "fatigueBase":368,
        "magickaModified":158,
        "fatigueModified":368,
        "healthBase":337,
        "magickaBase":158,
        "fatigueCurrent":368
      },
      "equipment":[],
      "inventory":[],
      "state":false
    },
    "29534-0":{
      "refId":"skaal_guard_a1",
      "location":{
        "posX":-159679.84375,
        "posZ":2984.8530273438,
        "posY":212846.96875,
        "rotX":0,
        "rotY":0,
        "rotZ":0
      },
      "stats":{
        "healthCurrent":394,
        "magickaCurrent":168,
        "healthModified":394,
        "fatigueBase":379,
        "fatigueModified":379,
        "healthBase":394,
        "magickaModified":168,
        "magickaBase":168,
        "fatigueCurrent":379
      },
      "equipment":{
        "0":{
          "refId":"bm_nordicmail_helmet",
          "count":1,
          "charge":-1,
          "enchantmentCharge":-1
        },
        "1":{
          "refId":"bm_nordicmail_cuirass",
          "count":1,
          "charge":-1,
          "enchantmentCharge":-1
        },
        "2":{
          "refId":"bm_nordicmail_greaves",
          "count":1,
          "charge":-1,
          "enchantmentCharge":-1
        },
        "3":{
          "refId":"bm_nordicmail_pauldronl",
          "count":1,
          "charge":-1,
          "enchantmentCharge":-1
        },
        "4":{
          "refId":"bm_nordicmail_pauldronr",
          "count":1,
          "charge":-1,
          "enchantmentCharge":-1
        },
        "5":{
          "refId":"bm_nordicmail_gauntletl",
          "count":1,
          "charge":-1,
          "enchantmentCharge":-1
        },
        "6":{
          "refId":"bm_nordicmail_gauntletr",
          "count":1,
          "charge":-1,
          "enchantmentCharge":-1
        },
        "7":{
          "refId":"bm_nordicmail_boots",
          "count":1,
          "charge":-1,
          "enchantmentCharge":-1
        },
        "16":{
          "refId":"bm nordic silver dagger",
          "count":1,
          "charge":-1,
          "enchantmentCharge":-1
        }
      },
      "inventory":[{
          "refId":"bm_nordicmail_gauntletr",
          "count":1,
          "charge":-1,
          "enchantmentCharge":-1,
          "soul":""
        },{
          "refId":"bm_nordicmail_gauntletl",
          "count":1,
          "charge":-1,
          "enchantmentCharge":-1,
          "soul":""
        },{
          "refId":"bm bear boots",
          "count":1,
          "charge":-1,
          "enchantmentCharge":-1,
          "soul":""
        },{
          "refId":"bm_nordicmail_boots",
          "count":1,
          "charge":-1,
          "enchantmentCharge":-1,
          "soul":""
        },{
          "refId":"bm_nordicmail_greaves",
          "count":1,
          "charge":-1,
          "enchantmentCharge":-1,
          "soul":""
        },{
          "refId":"bm_nordicmail_pauldronr",
          "count":1,
          "charge":-1,
          "enchantmentCharge":-1,
          "soul":""
        },{
          "refId":"bm_nordicmail_pauldronl",
          "count":1,
          "charge":-1,
          "enchantmentCharge":-1,
          "soul":""
        },{
          "refId":"bm_nordicmail_cuirass",
          "count":1,
          "charge":-1,
          "enchantmentCharge":-1,
          "soul":""
        },{
          "refId":"bm_nordicmail_helmet",
          "count":1,
          "charge":-1,
          "enchantmentCharge":-1,
          "soul":""
        },{
          "refId":"bm nordic silver dagger",
          "count":1,
          "charge":-1,
          "enchantmentCharge":-1,
          "soul":""
        }]
    },
    "29537-0":{
      "refId":"skaal_guard_a4",
      "location":{
        "posX":-160089.390625,
        "posZ":2997.6867675781,
        "posY":211846.78125,
        "rotX":0,
        "rotY":0,
        "rotZ":2.3000001907349
      },
      "stats":{
        "healthCurrent":394,
        "magickaCurrent":168,
        "healthModified":394,
        "fatigueBase":379,
        "fatigueModified":379,
        "healthBase":394,
        "magickaModified":168,
        "magickaBase":168,
        "fatigueCurrent":379
      },
      "equipment":{
        "0":{
          "refId":"bm_nordicmail_helmet",
          "count":1,
          "charge":-1,
          "enchantmentCharge":-1
        },
        "1":{
          "refId":"bm_nordicmail_cuirass",
          "count":1,
          "charge":-1,
          "enchantmentCharge":-1
        },
        "2":{
          "refId":"bm_nordicmail_greaves",
          "count":1,
          "charge":-1,
          "enchantmentCharge":-1
        },
        "3":{
          "refId":"bm_nordicmail_pauldronl",
          "count":1,
          "charge":-1,
          "enchantmentCharge":-1
        },
        "4":{
          "refId":"bm_nordicmail_pauldronr",
          "count":1,
          "charge":-1,
          "enchantmentCharge":-1
        },
        "5":{
          "refId":"bm_nordicmail_gauntletl",
          "count":1,
          "charge":-1,
          "enchantmentCharge":-1
        },
        "6":{
          "refId":"bm_nordicmail_gauntletr",
          "count":1,
          "charge":-1,
          "enchantmentCharge":-1
        },
        "7":{
          "refId":"bm_nordicmail_boots",
          "count":1,
          "charge":-1,
          "enchantmentCharge":-1
        },
        "16":{
          "refId":"bm nordic silver shortsword",
          "count":1,
          "charge":-1,
          "enchantmentCharge":-1
        }
      },
      "inventory":[{
          "refId":"bm_nordicmail_gauntletr",
          "count":1,
          "charge":-1,
          "enchantmentCharge":-1,
          "soul":""
        },{
          "refId":"bm_nordicmail_gauntletl",
          "count":1,
          "charge":-1,
          "enchantmentCharge":-1,
          "soul":""
        },{
          "refId":"bm bear boots",
          "count":1,
          "charge":-1,
          "enchantmentCharge":-1,
          "soul":""
        },{
          "refId":"bm_nordicmail_boots",
          "count":1,
          "charge":-1,
          "enchantmentCharge":-1,
          "soul":""
        },{
          "refId":"bm_nordicmail_greaves",
          "count":1,
          "charge":-1,
          "enchantmentCharge":-1,
          "soul":""
        },{
          "refId":"bm_nordicmail_pauldronr",
          "count":1,
          "charge":-1,
          "enchantmentCharge":-1,
          "soul":""
        },{
          "refId":"bm_nordicmail_pauldronl",
          "count":1,
          "charge":-1,
          "enchantmentCharge":-1,
          "soul":""
        },{
          "refId":"bm_nordicmail_cuirass",
          "count":1,
          "charge":-1,
          "enchantmentCharge":-1,
          "soul":""
        },{
          "refId":"bm_nordicmail_helmet",
          "count":1,
          "charge":-1,
          "enchantmentCharge":-1,
          "soul":""
        },{
          "refId":"bm nordic silver shortsword",
          "count":1,
          "charge":-1,
          "enchantmentCharge":-1,
          "soul":""
        }]
    },
    "11535-0":{
      "refId":"horski tallowhand",
      "location":{
        "posX":-157973.375,
        "posZ":3023.4106445313,
        "posY":210022.3125,
        "rotX":-0.013243544846773,
        "rotY":0,
        "rotZ":2.9322025775909
      },
      "stats":{
        "healthCurrent":322,
        "magickaCurrent":120,
        "healthModified":322,
        "fatigueBase":380,
        "fatigueModified":380,
        "healthBase":322,
        "magickaModified":120,
        "magickaBase":120,
        "fatigueCurrent":380
      },
      "equipment":{
        "2":{
          "refId":"bm bear greaves",
          "count":1,
          "charge":-1,
          "enchantmentCharge":-1
        },
        "7":{
          "refId":"bm bear boots",
          "count":1,
          "charge":-1,
          "enchantmentCharge":-1
        },
        "8":{
          "refId":"bm_nordic01_shirt",
          "count":1,
          "charge":-1,
          "enchantmentCharge":-1
        },
        "16":{
          "refId":"bm nordic silver longsword",
          "count":1,
          "charge":-1,
          "enchantmentCharge":-1
        }
      },
      "inventory":[{
          "refId":"bm bear boots",
          "count":1,
          "charge":-1,
          "enchantmentCharge":-1,
          "soul":""
        },{
          "refId":"bm bear greaves",
          "count":1,
          "charge":-1,
          "enchantmentCharge":-1,
          "soul":""
        },{
          "refId":"bm_nordic01_shirt",
          "count":1,
          "charge":-1,
          "enchantmentCharge":-1,
          "soul":""
        },{
          "refId":"bm nordic silver longsword",
          "count":1,
          "charge":-1,
          "enchantmentCharge":-1,
          "soul":""
        }]
    },
    "26426-0":{
      "refId":"bm_werewolf_skaal1e3",
      "location":{
        "posX":-158691.171875,
        "posZ":2929,
        "posY":212221.890625,
        "rotX":0,
        "rotY":0,
        "rotZ":0
      },
      "stats":{
        "healthCurrent":337,
        "magickaCurrent":158,
        "healthModified":337,
        "fatigueBase":368,
        "magickaModified":158,
        "fatigueModified":368,
        "healthBase":337,
        "magickaBase":158,
        "fatigueCurrent":368
      },
      "equipment":[],
      "inventory":[],
      "state":false
    },
    "32996-0":{
      "refId":"bm_wolf_caenlorn2",
      "location":{
        "posX":-159628.71875,
        "posZ":2963.8442382813,
        "posY":209737.875,
        "rotX":0,
        "rotY":0,
        "rotZ":0.10000001639128
      },
      "stats":{
        "healthCurrent":800,
        "magickaCurrent":50,
        "healthModified":800,
        "fatigueBase":1000,
        "fatigueModified":1000,
        "healthBase":800,
        "magickaModified":50,
        "magickaBase":50,
        "fatigueCurrent":1000
      },
      "inventory":[]
    },
    "14628-0":{
      "refId":"bm_werewolf_skaal1a3",
      "location":{
        "posX":-159557.921875,
        "posZ":2973.4272460938,
        "posY":212705.90625,
        "rotX":0,
        "rotY":0,
        "rotZ":0
      },
      "stats":{
        "healthCurrent":337,
        "magickaCurrent":158,
        "healthModified":337,
        "fatigueBase":368,
        "magickaModified":158,
        "fatigueModified":368,
        "healthBase":337,
        "magickaBase":158,
        "fatigueCurrent":368
      },
      "equipment":[],
      "inventory":[],
      "state":false
    },
    "29536-0":{
      "refId":"skaal_guard_a3",
      "location":{
        "posX":-159023.53125,
        "posZ":2980.0278320313,
        "posY":211678.953125,
        "rotX":0,
        "rotY":0,
        "rotZ":4.4831857681274
      },
      "stats":{
        "healthCurrent":394,
        "magickaCurrent":168,
        "healthModified":394,
        "fatigueBase":379,
        "fatigueModified":379,
        "healthBase":394,
        "magickaModified":168,
        "magickaBase":168,
        "fatigueCurrent":379
      },
      "equipment":{
        "0":{
          "refId":"bm_nordicmail_helmet",
          "count":1,
          "charge":-1,
          "enchantmentCharge":-1
        },
        "1":{
          "refId":"bm_nordicmail_cuirass",
          "count":1,
          "charge":-1,
          "enchantmentCharge":-1
        },
        "2":{
          "refId":"bm_nordicmail_greaves",
          "count":1,
          "charge":-1,
          "enchantmentCharge":-1
        },
        "3":{
          "refId":"bm_nordicmail_pauldronl",
          "count":1,
          "charge":-1,
          "enchantmentCharge":-1
        },
        "4":{
          "refId":"bm_nordicmail_pauldronr",
          "count":1,
          "charge":-1,
          "enchantmentCharge":-1
        },
        "5":{
          "refId":"bm_nordicmail_gauntletl",
          "count":1,
          "charge":-1,
          "enchantmentCharge":-1
        },
        "6":{
          "refId":"bm_nordicmail_gauntletr",
          "count":1,
          "charge":-1,
          "enchantmentCharge":-1
        },
        "7":{
          "refId":"bm_nordicmail_boots",
          "count":1,
          "charge":-1,
          "enchantmentCharge":-1
        },
        "16":{
          "refId":"bm nordic silver claymore",
          "count":1,
          "charge":-1,
          "enchantmentCharge":-1
        }
      },
      "inventory":[{
          "refId":"bm_nordicmail_gauntletr",
          "count":1,
          "charge":-1,
          "enchantmentCharge":-1,
          "soul":""
        },{
          "refId":"bm_nordicmail_gauntletl",
          "count":1,
          "charge":-1,
          "enchantmentCharge":-1,
          "soul":""
        },{
          "refId":"bm bear boots",
          "count":1,
          "charge":-1,
          "enchantmentCharge":-1,
          "soul":""
        },{
          "refId":"bm_nordicmail_boots",
          "count":1,
          "charge":-1,
          "enchantmentCharge":-1,
          "soul":""
        },{
          "refId":"bm_nordicmail_greaves",
          "count":1,
          "charge":-1,
          "enchantmentCharge":-1,
          "soul":""
        },{
          "refId":"bm_nordicmail_pauldronr",
          "count":1,
          "charge":-1,
          "enchantmentCharge":-1,
          "soul":""
        },{
          "refId":"bm_nordicmail_pauldronl",
          "count":1,
          "charge":-1,
          "enchantmentCharge":-1,
          "soul":""
        },{
          "refId":"bm_nordicmail_cuirass",
          "count":1,
          "charge":-1,
          "enchantmentCharge":-1,
          "soul":""
        },{
          "refId":"bm_nordicmail_helmet",
          "count":1,
          "charge":-1,
          "enchantmentCharge":-1,
          "soul":""
        },{
          "refId":"bm nordic silver claymore",
          "count":1,
          "charge":-1,
          "enchantmentCharge":-1,
          "soul":""
        }]
    },
    "11537-0":{
      "refId":"bm_wolf_caenlorn1",
      "location":{
        "posX":-159559.390625,
        "posZ":2969.0002441406,
        "posY":209449.46875,
        "rotX":0,
        "rotY":0,
        "rotZ":5.0831866264343
      },
      "stats":{
        "healthCurrent":800,
        "magickaCurrent":50,
        "healthModified":800,
        "fatigueBase":1000,
        "fatigueModified":1000,
        "healthBase":800,
        "magickaModified":50,
        "magickaBase":50,
        "fatigueCurrent":1000
      },
      "inventory":[]
    },
    "11538-0":{
      "refId":"bm_wolf_caenlorn3",
      "location":{
        "posX":-159714,
        "posZ":2961.7600097656,
        "posY":209528.21875,
        "rotX":0,
        "rotY":0,
        "rotZ":2.9999997615814
      },
      "stats":{
        "healthCurrent":800,
        "magickaCurrent":50,
        "healthModified":800,
        "fatigueBase":1000,
        "fatigueModified":1000,
        "healthBase":800,
        "magickaModified":50,
        "magickaBase":50,
        "fatigueCurrent":1000
      },
      "inventory":[]
    },
    "29535-0":{
      "refId":"skaal_guard_a2",
      "location":{
        "posX":-158287.09375,
        "posZ":2929,
        "posY":212739.71875,
        "rotX":0,
        "rotY":0,
        "rotZ":5.1831860542297
      },
      "stats":{
        "healthCurrent":394,
        "magickaCurrent":168,
        "healthModified":394,
        "fatigueBase":379,
        "fatigueModified":379,
        "healthBase":394,
        "magickaModified":168,
        "magickaBase":168,
        "fatigueCurrent":379
      },
      "equipment":{
        "0":{
          "refId":"bm_nordicmail_helmet",
          "count":1,
          "charge":-1,
          "enchantmentCharge":-1
        },
        "1":{
          "refId":"bm_nordicmail_cuirass",
          "count":1,
          "charge":-1,
          "enchantmentCharge":-1
        },
        "2":{
          "refId":"bm_nordicmail_greaves",
          "count":1,
          "charge":-1,
          "enchantmentCharge":-1
        },
        "3":{
          "refId":"bm_nordicmail_pauldronl",
          "count":1,
          "charge":-1,
          "enchantmentCharge":-1
        },
        "4":{
          "refId":"bm_nordicmail_pauldronr",
          "count":1,
          "charge":-1,
          "enchantmentCharge":-1
        },
        "5":{
          "refId":"bm_nordicmail_gauntletl",
          "count":1,
          "charge":-1,
          "enchantmentCharge":-1
        },
        "6":{
          "refId":"bm_nordicmail_gauntletr",
          "count":1,
          "charge":-1,
          "enchantmentCharge":-1
        },
        "7":{
          "refId":"bm_nordicmail_boots",
          "count":1,
          "charge":-1,
          "enchantmentCharge":-1
        },
        "16":{
          "refId":"bm nordic silver dagger",
          "count":1,
          "charge":-1,
          "enchantmentCharge":-1
        }
      },
      "inventory":[{
          "refId":"bm_nordicmail_gauntletr",
          "count":1,
          "charge":-1,
          "enchantmentCharge":-1,
          "soul":""
        },{
          "refId":"bm_nordicmail_gauntletl",
          "count":1,
          "charge":-1,
          "enchantmentCharge":-1,
          "soul":""
        },{
          "refId":"bm bear boots",
          "count":1,
          "charge":-1,
          "enchantmentCharge":-1,
          "soul":""
        },{
          "refId":"bm_nordicmail_boots",
          "count":1,
          "charge":-1,
          "enchantmentCharge":-1,
          "soul":""
        },{
          "refId":"bm_nordicmail_greaves",
          "count":1,
          "charge":-1,
          "enchantmentCharge":-1,
          "soul":""
        },{
          "refId":"bm_nordicmail_pauldronr",
          "count":1,
          "charge":-1,
          "enchantmentCharge":-1,
          "soul":""
        },{
          "refId":"bm_nordicmail_pauldronl",
          "count":1,
          "charge":-1,
          "enchantmentCharge":-1,
          "soul":""
        },{
          "refId":"bm_nordicmail_cuirass",
          "count":1,
          "charge":-1,
          "enchantmentCharge":-1,
          "soul":""
        },{
          "refId":"bm_nordicmail_helmet",
          "count":1,
          "charge":-1,
          "enchantmentCharge":-1,
          "soul":""
        },{
          "refId":"bm nordic silver dagger",
          "count":1,
          "charge":-1,
          "enchantmentCharge":-1,
          "soul":""
        }]
    },
    "11536-0":{
      "refId":"alvring whitebeard",
      "location":{
        "posX":-161320.9375,
        "posZ":2962.0876464844,
        "posY":211495.59375,
        "rotX":-0.11350633203983,
        "rotY":0,
        "rotZ":2.3500463962555
      },
      "stats":{
        "healthCurrent":352,
        "magickaCurrent":128,
        "healthModified":352,
        "fatigueBase":374,
        "fatigueModified":374,
        "healthBase":352,
        "magickaModified":128,
        "magickaBase":128,
        "fatigueCurrent":374
      },
      "equipment":{
        "0":{
          "refId":"bm bear helmet",
          "count":1,
          "charge":-1,
          "enchantmentCharge":-1
        },
        "1":{
          "refId":"bm bear cuirass",
          "count":1,
          "charge":-1,
          "enchantmentCharge":-1
        },
        "2":{
          "refId":"bm bear greaves",
          "count":1,
          "charge":-1,
          "enchantmentCharge":-1
        },
        "3":{
          "refId":"bm bear left pauldron",
          "count":1,
          "charge":-1,
          "enchantmentCharge":-1
        },
        "4":{
          "refId":"bm bear right pauldron",
          "count":1,
          "charge":-1,
          "enchantmentCharge":-1
        },
        "5":{
          "refId":"bm bear left gauntlet",
          "count":1,
          "charge":-1,
          "enchantmentCharge":-1
        },
        "6":{
          "refId":"bm bear right gauntlet",
          "count":1,
          "charge":-1,
          "enchantmentCharge":-1
        },
        "7":{
          "refId":"bm bear boots",
          "count":1,
          "charge":-1,
          "enchantmentCharge":-1
        },
        "16":{
          "refId":"bm nordic silver mace",
          "count":1,
          "charge":-1,
          "enchantmentCharge":-1
        }
      },
      "inventory":[{
          "refId":"bm bear right gauntlet",
          "count":1,
          "charge":-1,
          "enchantmentCharge":-1,
          "soul":""
        },{
          "refId":"bm bear left gauntlet",
          "count":1,
          "charge":-1,
          "enchantmentCharge":-1,
          "soul":""
        },{
          "refId":"bm bear boots",
          "count":1,
          "charge":-1,
          "enchantmentCharge":-1,
          "soul":""
        },{
          "refId":"bm bear greaves",
          "count":1,
          "charge":-1,
          "enchantmentCharge":-1,
          "soul":""
        },{
          "refId":"bm bear right pauldron",
          "count":1,
          "charge":-1,
          "enchantmentCharge":-1,
          "soul":""
        },{
          "refId":"bm bear left pauldron",
          "count":1,
          "charge":-1,
          "enchantmentCharge":-1,
          "soul":""
        },{
          "refId":"bm bear cuirass",
          "count":1,
          "charge":-1,
          "enchantmentCharge":-1,
          "soul":""
        },{
          "refId":"bm bear helmet",
          "count":1,
          "charge":-1,
          "enchantmentCharge":-1,
          "soul":""
        },{
          "refId":"bm nordic silver mace",
          "count":1,
          "charge":-1,
          "enchantmentCharge":-1,
          "soul":""
        }]
    },
    "30743-0":{
      "refId":"bm_werewolf_skaal1g3",
      "location":{
        "posX":-159489.046875,
        "posZ":2992.5690917969,
        "posY":211977.765625,
        "rotX":0,
        "rotY":0,
        "rotZ":0
      },
      "stats":{
        "healthCurrent":337,
        "magickaCurrent":158,
        "healthModified":337,
        "fatigueBase":368,
        "magickaModified":158,
        "fatigueModified":368,
        "healthBase":337,
        "magickaBase":158,
        "fatigueCurrent":368
      },
      "equipment":[],
      "inventory":[],
      "state":false
    }
  }
}