{
  "packets":{
    "actorList":["0-2809","0-2810","0-2811","0-2812"],
    "ai":[],
    "cellChangeFrom":[],
    "cellChangeTo":[],
    "container":["135182-0","135183-0","135184-0","135185-0","455817-0","455820-0","455827-0","455829-0","455860-0","455861-0","455868-0","455881-0","0-2811"],
    "death":["0-2811"],
    "delete":[],
    "doorState":[],
    "equipment":[],
    "lock":[],
    "place":[],
    "position":["0-2809","0-2810","0-2811","0-2812"],
    "scale":[],
    "spawn":["0-2809","0-2810","0-2811","0-2812"],
    "state":[],
    "statsDynamic":["0-2809","0-2810","0-2811","0-2812"],
    "trap":[]
  },
  "entry":{
    "creationTime":1569091247,
    "description":"9, -9"
  },
  "lastVisit":{
    "Dizzy":1569093821,
    "Dr,Kups":1569091999
  },
  "recordLinks":[],
  "objectData":{
    "0-2811":{
      "refId":"mudcrab-diseased",
      "location":{
        "posX":80237.1015625,
        "posZ":199.36215209961,
        "posY":-73173.8046875,
        "rotX":-0.06899482011795,
        "rotY":0,
        "rotZ":1.3727157115936
      },
      "stats":{
        "healthCurrent":0,
        "magickaCurrent":5,
        "healthModified":15,
        "fatigueBase":55,
        "fatigueModified":55,
        "healthBase":15,
        "magickaModified":5,
        "magickaBase":5,
        "fatigueCurrent":55
      },
      "inventory":[{
          "refId":"ingred_crab_meat_01",
          "count":1,
          "charge":-1,
          "enchantmentCharge":-1,
          "soul":""
        }],
      "killer":{
        "player":"Dr,Kups"
      }
    },
    "455861-0":{
      "refId":"kollop_03_pearl",
      "inventory":[]
    },
    "455881-0":{
      "refId":"kollop_02_pearl",
      "inventory":[{
          "refId":"ingred_pearl_01",
          "count":1,
          "charge":-1,
          "enchantmentCharge":-1,
          "soul":""
        }]
    },
    "135183-0":{
      "refId":"flora_kreshweed_02",
      "inventory":[{
          "refId":"ingred_kresh_fiber_01",
          "count":1,
          "charge":-1,
          "enchantmentCharge":-1,
          "soul":""
        }]
    },
    "455868-0":{
      "refId":"kollop_02_pearl",
      "inventory":[{
          "refId":"ingred_pearl_01",
          "count":1,
          "charge":-1,
          "enchantmentCharge":-1,
          "soul":""
        }]
    },
    "135185-0":{
      "refId":"flora_kreshweed_01",
      "inventory":[{
          "refId":"ingred_kresh_fiber_01",
          "count":1,
          "charge":-1,
          "enchantmentCharge":-1,
          "soul":""
        }]
    },
    "455829-0":{
      "refId":"kollop_03_pearl",
      "inventory":[{
          "refId":"ingred_pearl_01",
          "count":1,
          "charge":-1,
          "enchantmentCharge":-1,
          "soul":""
        }]
    },
    "455817-0":{
      "refId":"kollop_02_pearl",
      "inventory":[{
          "refId":"ingred_pearl_01",
          "count":1,
          "charge":-1,
          "enchantmentCharge":-1,
          "soul":""
        }]
    },
    "135184-0":{
      "refId":"flora_kreshweed_03",
      "inventory":[{
          "refId":"ingred_kresh_fiber_01",
          "count":1,
          "charge":-1,
          "enchantmentCharge":-1,
          "soul":""
        }]
    },
    "135182-0":{
      "refId":"flora_kreshweed_01",
      "inventory":[{
          "refId":"ingred_kresh_fiber_01",
          "count":1,
          "charge":-1,
          "enchantmentCharge":-1,
          "soul":""
        }]
    },
    "0-2810":{
      "refId":"mudcrab",
      "location":{
        "posX":80800.5078125,
        "posZ":173.80390930176,
        "posY":-66025.703125,
        "rotX":0.043808050453663,
        "rotY":0,
        "rotZ":1.7215411663055
      },
      "stats":{
        "healthCurrent":15,
        "magickaCurrent":5,
        "healthModified":15,
        "fatigueBase":400,
        "fatigueModified":400,
        "healthBase":15,
        "magickaModified":5,
        "magickaBase":5,
        "fatigueCurrent":400
      }
    },
    "455860-0":{
      "refId":"kollop_03_pearl",
      "inventory":[{
          "refId":"ingred_pearl_01",
          "count":1,
          "charge":-1,
          "enchantmentCharge":-1,
          "soul":""
        }]
    },
    "455820-0":{
      "refId":"kollop_02_pearl",
      "inventory":[{
          "refId":"ingred_pearl_01",
          "count":1,
          "charge":-1,
          "enchantmentCharge":-1,
          "soul":""
        }]
    },
    "0-2809":{
      "refId":"mudcrab-diseased",
      "location":{
        "posX":76929.765625,
        "posZ":170.33056640625,
        "posY":-68054.4453125,
        "rotX":-0.045276552438736,
        "rotY":0,
        "rotZ":0.93913102149963
      },
      "stats":{
        "healthCurrent":15,
        "magickaCurrent":5,
        "healthModified":15,
        "fatigueBase":30,
        "fatigueModified":30,
        "healthBase":15,
        "magickaModified":5,
        "magickaBase":5,
        "fatigueCurrent":30
      }
    },
    "0-2812":{
      "refId":"slaughterfish_small",
      "location":{
        "posX":79327.2578125,
        "posZ":-359.16387939453,
        "posY":-67433.828125,
        "rotX":0.00027722306549549,
        "rotY":0,
        "rotZ":2.7390406131744
      },
      "stats":{
        "healthCurrent":15,
        "magickaCurrent":10,
        "healthModified":15,
        "fatigueBase":300,
        "fatigueModified":300,
        "healthBase":15,
        "magickaModified":10,
        "magickaBase":10,
        "fatigueCurrent":299.9582824707
      }
    },
    "455827-0":{
      "refId":"kollop_03_pearl",
      "inventory":[]
    }
  }
}